autolab_core/__init__.py
autolab_core/camera_intrinsics.py
autolab_core/chessboard_registration.py
autolab_core/completer.py
autolab_core/constants.py
autolab_core/csv_model.py
autolab_core/data_stream_recorder.py
autolab_core/data_stream_syncer.py
autolab_core/detector.py
autolab_core/dist_metrics.py
autolab_core/dual_quaternion.py
autolab_core/experiment_logger.py
autolab_core/feature_matcher.py
autolab_core/features.py
autolab_core/image.py
autolab_core/json_serialization.py
autolab_core/learning_analysis.py
autolab_core/logger.py
autolab_core/orthographic_intrinsics.py
autolab_core/point_registration.py
autolab_core/points.py
autolab_core/primitives.py
autolab_core/random_variables.py
autolab_core/rigid_transformations.py
autolab_core/tensor_dataset.py
autolab_core/transformations.py
autolab_core/utils.py
autolab_core/version.py
autolab_core/yaml_config.py
autolab_core-1.1.1.dist-info/LICENSE
autolab_core-1.1.1.dist-info/METADATA
autolab_core-1.1.1.dist-info/WHEEL
autolab_core-1.1.1.dist-info/top_level.txt
autolab_core-1.1.1.dist-info/RECORD
